README.md
setup.py
apureza/__init__.py
apureza/conversion.py
apureza/exceptions.py
apureza/geocoding.py
apureza/mltools.py
apureza/urban.py
apureza.egg-info/PKG-INFO
apureza.egg-info/SOURCES.txt
apureza.egg-info/dependency_links.txt
apureza.egg-info/not-zip-safe
apureza.egg-info/requires.txt
apureza.egg-info/top_level.txt