Metadata-Version: 2.1
Name: apureza
Version: 0.1.21
Summary: Apureza project API
Home-page: http://github.com/benjaminpillot/apureza
Author: Benjamin Pillot
Author-email: benjaminpillot@riseup.net
License: GNU GPL v3.0
Platform: UNKNOWN
Requires-Python: >=3
